<screen name="EMCMediaCenter" position="0,552" size="1280,150" title="InfoBar" backgroundColor="transparent" flags="wfNoBorder">
	<ePixmap position="0,0" zPosition="-1" size="1280,150" pixmap="/usr/lib/enigma2/python/Plugins/Extensions/EnhancedMovieCenter/img/EMCMoviePlayer/CoolInfobar.png" />

	<widget source="session.CurrentService" render="Label" font="Regular;22" position="40,8" size="55,30" halign="right" foregroundColor="#00e5b243" backgroundColor="#00000000" transparent="1">
		<convert type="ServiceInfo">VideoWidth</convert>
	</widget>
	<eLabel text="x" font="Regular;20" position="102,8" size="15,30" halign="center" foregroundColor="#00e5b243" backgroundColor="#00000000" transparent="1" />
	<widget source="session.CurrentService" render="Label" font="Regular;22" position="125,8" size="55,30" halign="left" foregroundColor="#00e5b243" backgroundColor="#00000000" transparent="1">
		<convert type="ServiceInfo">VideoHeight</convert>
	</widget>
	<widget source="session.CurrentService" render="Label" position="200,5" size="880,30" font="Regular;26" valign="top" halign="center" noWrap="1" backgroundColor="#00000000" transparent="1">
		<convert type="ServiceName">Name</convert>
	</widget>
	<widget source="global.CurrentTime" render="Label" position="1110,8" size="100,30" font="Regular;22" valign="top" halign="left" foregroundColor="#00e5b243" backgroundColor="#00000000" transparent="1">
		<convert type="ClockToText">Format:%H:%M:%S</convert>
	</widget>

	<ePixmap position="180,59" size="900,30" pixmap="/usr/lib/enigma2/python/Plugins/Extensions/EnhancedMovieCenter/img/EMCMoviePlayer/CoolSlider.png" zPosition="3" alphatest="blend" />
	<ePixmap position="200,62" size="860,18" pixmap="/usr/lib/enigma2/python/Plugins/Extensions/EnhancedMovieCenter/img/EMCMoviePlayer/CoolPointerBG.png" zPosition="1" alphatest="blend" />
	<widget source="session.CurrentService" render="PositionGauge" position="218,50" size="828,28" zPosition="2" pointer="/usr/lib/enigma2/python/Plugins/Extensions/EnhancedMovieCenter/img/EMCMoviePlayer/CoolPointer.png:828,-2" transparent="1" >
		<convert type="EMCServicePosition">Gauge</convert>
	</widget>

	<widget source="session.CurrentService" render="Label" position="230,85" size="100,30" font="Regular;22" halign="left" backgroundColor="#00000000" transparent="1">
		<convert type="EMCServicePosition">Position</convert>
	</widget>
	<widget source="session.CurrentService" render="Label" position="590,85" size="100,30" font="Regular;22" halign="center" backgroundColor="#00000000" transparent="1">
		<convert type="EMCServicePosition">Length</convert>
	</widget>
	<widget source="session.CurrentService" render="Label" position="930,85" size="100,30" font="Regular;22" halign="right" backgroundColor="#00000000" transparent="1">
		<convert type="EMCServicePosition">Remaining,Negate</convert>
	</widget>


	<ePixmap pixmap="/usr/lib/enigma2/python/Plugins/Extensions/EnhancedMovieCenter/img/EMCMoviePlayer/format_off.png" position="50,125" size="40,20" zPosition="1" alphatest="blend" />
	<widget source="session.CurrentService" render="Pixmap" pixmap="/usr/lib/enigma2/python/Plugins/Extensions/EnhancedMovieCenter/img/EMCMoviePlayer/format_on.png" position="50,125" size="40,20" zPosition="2" alphatest="blend">
		<convert type="ServiceInfo">IsWidescreen</convert>
		<convert type="ConditionalShowHide" />
	</widget>

	<ePixmap position="120,128" size="26,16" pixmap="skin_default/icons/icon_dolby.png" zPosition="3" alphatest="on" />
	<widget name="audioLabel" position="155,125" size="100,22" font="Regular;18" backgroundColor="#00000000" zPosition="3" transparent="1" />

	<widget name="chapterLabel" position="350,125" size="580,30" font="Regular;22" halign="center" foregroundColor="#00e5b243" backgroundColor="#00000000" transparent="1" />
	<!-- Subtitel Label only for DVD -->
	<widget name="subtitleLabel" position="1009,125" size="70,22" zPosition="3" halign="right" font="Regular;18" backgroundColor="#00000000" transparent="1" />

	<ePixmap pixmap="/usr/lib/enigma2/python/Plugins/Extensions/EnhancedMovieCenter/img/EMCMoviePlayer/rec_off.png" position="1104,125" size="28,20" zPosition="1" alphatest="on" />
	<widget source="session.RecordState" render="Pixmap" pixmap="/usr/lib/enigma2/python/Plugins/Extensions/EnhancedMovieCenter/img/EMCMoviePlayer/rec_on.png" position="1104,125" size="28,20" zPosition="2" alphatest="on">
		<convert type="ConditionalShowHide">Blink</convert>
	</widget>

	<ePixmap pixmap="/usr/lib/enigma2/python/Plugins/Extensions/EnhancedMovieCenter/img/EMCMoviePlayer/dolby_off.png" position="1159,125" size="57,20" zPosition="1" alphatest="blend" />
	<widget source="session.CurrentService" render="Pixmap" pixmap="/usr/lib/enigma2/python/Plugins/Extensions/EnhancedMovieCenter/img/EMCMoviePlayer/dolby_on.png" position="1159,125" size="57,20" zPosition="2" alphatest="blend">
		<convert type="ServiceInfo">IsMultichannel</convert>
		<convert type="ConditionalShowHide" />
	</widget>

</screen>
